smartquery/__init__.py
smartquery/__main__.py
smartquery/ast_ops.py
smartquery/custom_types.py
smartquery/exceptions.py
smartquery/functions.py
smartquery/lexer.py
smartquery/repl.py
smartquery/rules.py
smartquery/scoped_dict.py
smartquery/sq_parser.py
smartquery/utils.py
smartquery/vm_state.py
smartquery/gen/__init__.py
smartquery/gen/lextab.py
smartquery/gen/parsetab.py
smartquery/ply/__init__.py
smartquery/ply/lex.py
smartquery/ply/yacc.py
smartquery-0.1.9.dist-info/LICENSE.md
smartquery-0.1.9.dist-info/METADATA
smartquery-0.1.9.dist-info/WHEEL
smartquery-0.1.9.dist-info/top_level.txt
smartquery-0.1.9.dist-info/RECORD
